bradleystevenson2015_database/.gitignore
bradleystevenson2015_database/__init__.py
bradleystevenson2015_database/database.py
bradleystevenson2015_database-0.0.41.dist-info/METADATA
bradleystevenson2015_database-0.0.41.dist-info/WHEEL
bradleystevenson2015_database-0.0.41.dist-info/licenses/LICENSE
bradleystevenson2015_database-0.0.41.dist-info/RECORD
