Metadata-Version: 2.1
Name: bradleystevenson2015_database
Version: 0.0.41
Summary: A simplified interface for using databases using tables
Project-URL: Homepage, https://github.com/pypa/sampleproject
Project-URL: Bug Tracker, https://github.com/pypa/sampleproject/issues
Author-email: Bradley Stevenson <bradleystevenson2015@gmail.com>
License-File: LICENSE
Classifier: License :: OSI Approved :: MIT License
Classifier: Operating System :: OS Independent
Classifier: Programming Language :: Python :: 3
Requires-Python: >=3.7
